{"cfgs":{"allTime":648,"playTime":1000,"inter":[108,108,108,108,108,108],"rotate360":false,"offsetX":0,"releaseFrame":0,"blendMode":"normal","releaseTime":0,"scale":1.14,"offset":{"45":[[-206.4,-181.7],[-218.8,-185.1],[-222.7,-187.1],[-221.6,-181.7],[-227.8,-182.4],[-218.9,-178.7]]},"effectTime":0,"effectFrame":0,"offsetY":"0","horseY":0,"repeatPlay":false},"frames":{"45_0.png":{"frame":{"w":281,"x":0,"h":272,"y":282}},"45_4.png":{"frame":{"w":313,"x":303,"h":264,"y":0}},"45_2.png":{"frame":{"w":303,"x":303,"h":271,"y":265}},"45_3.png":{"frame":{"w":315,"x":607,"h":260,"y":270}},"45_5.png":{"frame":{"w":313,"x":617,"h":269,"y":0}},"45_1.png":{"frame":{"w":302,"x":0,"h":281,"y":0}}},"meta":{"image":"45.png"}}