{"frames":{"180_7.png":{"frame":{"w":136,"x":144,"h":179,"y":0}},"180_0.png":{"frame":{"w":122,"x":126,"h":183,"y":180}},"180_4.png":{"frame":{"w":117,"x":376,"h":175,"y":353}},"180_1.png":{"frame":{"w":125,"x":0,"h":187,"y":177}},"180_3.png":{"frame":{"w":129,"x":376,"h":174,"y":178}},"180_5.png":{"frame":{"w":126,"x":249,"h":174,"y":180}},"180_6.png":{"frame":{"w":140,"x":281,"h":177,"y":0}},"180_2.png":{"frame":{"w":143,"x":0,"h":176,"y":0}}},"cfgs":{"rotate360":false,"inter":[125,125,125,125,125,125,125,125],"playTime":1000,"scale":1.14,"effectFrame":0,"effectTime":0,"releaseFrame":0,"allTime":1000,"horseY":0,"releaseTime":0,"offset":{"180":[["-59.6","-154.2"],["-59.6","-160.0"],["-66.2","-162.4"],["-60.9","-153.0"],["-57.4","-148.4"],["-64.4","-150.7"],["-72.5","-164.5"],["-66.9","-156.2"]]},"offsetX":0,"repeatPlay":false,"offsetY":"0","blendMode":"normal"},"meta":{"image":"180.png"}}