{"file":"sheet_weapon_1_1_1_1_4.png","frames":{
"1_4_6":{"x":177,"y":106,"w":53,"h":109,"offX":0,"offY":0,"sourceW":53,"sourceH":109},
"1_4_7":{"x":232,"y":106,"w":54,"h":107,"offX":0,"offY":0,"sourceW":54,"sourceH":107},
"1_4_8":{"x":1,"y":1,"w":56,"h":106,"offX":0,"offY":0,"sourceW":56,"sourceH":106},
"1_4_9":{"x":117,"y":1,"w":57,"h":103,"offX":0,"offY":0,"sourceW":57,"sourceH":103},
"1_4_0":{"x":1,"y":109,"w":58,"h":102,"offX":0,"offY":0,"sourceW":58,"sourceH":102},
"1_4_1":{"x":61,"y":108,"w":57,"h":103,"offX":0,"offY":0,"sourceW":57,"sourceH":103},
"1_4_2":{"x":59,"y":1,"w":56,"h":105,"offX":0,"offY":0,"sourceW":56,"sourceH":105},
"1_4_3":{"x":120,"y":106,"w":55,"h":106,"offX":0,"offY":0,"sourceW":55,"sourceH":106},
"1_4_4":{"x":288,"y":106,"w":53,"h":108,"offX":0,"offY":0,"sourceW":53,"sourceH":108},
"1_4_5":{"x":343,"y":106,"w":52,"h":109,"offX":0,"offY":0,"sourceW":52,"sourceH":109}}}