{"file":"sheet_wing_2_1_1_2_5.png","frames":{
"2_5_0":{"x":1,"y":98,"w":169,"h":92,"offX":0,"offY":0,"sourceW":169,"sourceH":92},
"2_5_1":{"x":1,"y":1,"w":173,"h":95,"offX":0,"offY":0,"sourceW":173,"sourceH":95},
"2_5_2":{"x":176,"y":1,"w":163,"h":97,"offX":0,"offY":0,"sourceW":163,"sourceH":97},
"2_5_3":{"x":172,"y":100,"w":144,"h":102,"offX":0,"offY":0,"sourceW":144,"sourceH":102},
"2_5_4":{"x":1,"y":296,"w":130,"h":103,"offX":0,"offY":0,"sourceW":130,"sourceH":103},
"2_5_5":{"x":1,"y":192,"w":135,"h":102,"offX":0,"offY":0,"sourceW":135,"sourceH":102},
"2_5_6":{"x":341,"y":99,"w":148,"h":103,"offX":0,"offY":0,"sourceW":148,"sourceH":103},
"2_5_7":{"x":341,"y":1,"w":161,"h":96,"offX":0,"offY":0,"sourceW":161,"sourceH":96}}}