{"frames":{"000.png":{"frame":{"h":202,"idx":0,"w":177,"x":290,"y":193},"sourceSize":{"h":512,"w":512},"spriteSourceSize":{"x":182,"y":153}},"001.png":{"frame":{"h":203,"idx":0,"w":175,"x":831,"y":402},"sourceSize":{"h":512,"w":512},"spriteSourceSize":{"x":184,"y":153}},"002.png":{"frame":{"h":203,"idx":0,"w":169,"x":661,"y":398},"sourceSize":{"h":512,"w":512},"spriteSourceSize":{"x":190,"y":153}},"003.png":{"frame":{"h":202,"idx":0,"w":163,"x":497,"y":398},"sourceSize":{"h":512,"w":512},"spriteSourceSize":{"x":196,"y":153}},"004.png":{"frame":{"h":203,"idx":0,"w":157,"x":339,"y":396},"sourceSize":{"h":512,"w":512},"spriteSourceSize":{"x":202,"y":153}},"005.png":{"frame":{"h":203,"idx":0,"w":151,"x":187,"y":396},"sourceSize":{"h":512,"w":512},"spriteSourceSize":{"x":208,"y":153}},"006.png":{"frame":{"h":202,"idx":0,"w":145,"x":852,"y":199},"sourceSize":{"h":512,"w":512},"spriteSourceSize":{"x":214,"y":153}},"007.png":{"frame":{"h":198,"idx":0,"w":139,"x":786,"y":0},"sourceSize":{"h":512,"w":512},"spriteSourceSize":{"x":220,"y":153}},"008.png":{"frame":{"h":198,"idx":0,"w":133,"x":718,"y":199},"sourceSize":{"h":512,"w":512},"spriteSourceSize":{"x":226,"y":153}},"009.png":{"frame":{"h":198,"idx":0,"w":127,"x":590,"y":199},"sourceSize":{"h":512,"w":512},"spriteSourceSize":{"x":232,"y":153}},"010.png":{"frame":{"h":198,"idx":0,"w":121,"x":468,"y":196},"sourceSize":{"h":512,"w":512},"spriteSourceSize":{"x":238,"y":153}},"011.png":{"frame":{"h":198,"idx":0,"w":117,"x":668,"y":0},"sourceSize":{"h":512,"w":512},"spriteSourceSize":{"x":242,"y":153}},"012.png":{"frame":{"h":198,"idx":0,"w":112,"x":0,"y":0},"sourceSize":{"h":512,"w":512},"spriteSourceSize":{"x":247,"y":153}},"013.png":{"frame":{"h":198,"idx":0,"w":107,"x":79,"y":385},"sourceSize":{"h":512,"w":512},"spriteSourceSize":{"x":252,"y":153}},"014.png":{"frame":{"h":198,"idx":0,"w":102,"x":187,"y":193},"sourceSize":{"h":512,"w":512},"spriteSourceSize":{"x":257,"y":153}},"015.png":{"frame":{"h":195,"idx":0,"w":97,"x":570,"y":0},"sourceSize":{"h":512,"w":512},"spriteSourceSize":{"x":262,"y":153}},"016.png":{"frame":{"h":192,"idx":0,"w":92,"x":477,"y":0},"sourceSize":{"h":512,"w":512},"spriteSourceSize":{"x":267,"y":153}},"017.png":{"frame":{"h":192,"idx":0,"w":87,"x":389,"y":0},"sourceSize":{"h":512,"w":512},"spriteSourceSize":{"x":272,"y":153}},"018.png":{"frame":{"h":192,"idx":0,"w":83,"x":305,"y":0},"sourceSize":{"h":512,"w":512},"spriteSourceSize":{"x":276,"y":153}},"019.png":{"frame":{"h":192,"idx":0,"w":78,"x":0,"y":199},"sourceSize":{"h":512,"w":512},"spriteSourceSize":{"x":281,"y":153}},"020.png":{"frame":{"h":192,"idx":0,"w":73,"x":113,"y":192},"sourceSize":{"h":512,"w":512},"spriteSourceSize":{"x":286,"y":153}},"021.png":{"frame":{"h":192,"idx":0,"w":68,"x":236,"y":0},"sourceSize":{"h":512,"w":512},"spriteSourceSize":{"x":291,"y":153}},"022.png":{"frame":{"h":191,"idx":0,"w":63,"x":172,"y":0},"sourceSize":{"h":512,"w":512},"spriteSourceSize":{"x":296,"y":154}},"023.png":{"frame":{"h":168,"idx":0,"w":58,"x":113,"y":0},"sourceSize":{"h":512,"w":512},"spriteSourceSize":{"x":301,"y":177}}},"meta":{"image":"fx_szhlyd.png","prefix":"fx_szhlyd/"}}