{"frames":{"90_1.png":{"frame":{"w":415,"x":419,"h":205,"y":0}},"90_4.png":{"frame":{"w":421,"x":417,"h":194,"y":408}},"90_5.png":{"frame":{"w":421,"x":419,"h":201,"y":206}},"90_0.png":{"frame":{"w":414,"x":0,"h":197,"y":410}},"90_7.png":{"frame":{"w":416,"x":0,"h":202,"y":207}},"90_2.png":{"frame":{"w":417,"x":420,"h":194,"y":603}},"90_6.png":{"frame":{"w":418,"x":0,"h":206,"y":0}},"90_3.png":{"frame":{"w":419,"x":0,"h":191,"y":608}}},"cfgs":{"rotate360":false,"inter":[125,125,125,125,125,125,125,125],"playTime":1000,"scale":1.14,"effectFrame":0,"effectTime":0,"releaseFrame":0,"allTime":1000,"horseY":0,"releaseTime":0,"offset":{"90":[["-233.7","-165.4"],["-235.0","-164.8"],["-237.0","-160.8"],["-239.0","-161.9"],["-241.0","-164.8"],["-241.4","-170.9"],["-238.5","-175.5"],["-235.6","-171.0"]]},"offsetX":0,"repeatPlay":false,"offsetY":"0","blendMode":"normal"},"meta":{"image":"90.png"}}