{"file":"sheet_wing_3_1_1_2_1.png","frames":{
"2_1_7":{"x":1,"y":148,"w":171,"h":137,"offX":0,"offY":0,"sourceW":171,"sourceH":137},
"2_1_0":{"x":1,"y":1,"w":188,"h":145,"offX":0,"offY":0,"sourceW":188,"sourceH":145},
"2_1_1":{"x":191,"y":1,"w":187,"h":143,"offX":0,"offY":0,"sourceW":187,"sourceH":143},
"2_1_2":{"x":191,"y":146,"w":171,"h":138,"offX":0,"offY":0,"sourceW":171,"sourceH":138},
"2_1_3":{"x":364,"y":146,"w":146,"h":135,"offX":0,"offY":0,"sourceW":146,"sourceH":135},
"2_1_4":{"x":380,"y":1,"w":118,"h":136,"offX":0,"offY":0,"sourceW":118,"sourceH":136},
"2_1_5":{"x":174,"y":286,"w":115,"h":133,"offX":0,"offY":0,"sourceW":115,"sourceH":133},
"2_1_6":{"x":364,"y":283,"w":137,"h":130,"offX":0,"offY":0,"sourceW":137,"sourceH":130}}}